setup.py
loglikelihood/__init__.py
loglikelihood.egg-info/PKG-INFO
loglikelihood.egg-info/SOURCES.txt
loglikelihood.egg-info/dependency_links.txt
loglikelihood.egg-info/not-zip-safe
loglikelihood.egg-info/top_level.txt