Metadata-Version: 1.0
Name: loglikelihood
Version: 0.1
Summary: A library for python to implement the 'Log Likelihood' and 'Root Log Likelihood' algorithms.
Home-page: https://github.com/Tom-Davidson/logLikelihood
Author: Tom Davidson
Author-email: tom@davidson.me.uk
License: MIT
Platform: UNKNOWN
